{
  "credit": "Made with Blockbench",
  "parent": "block/block",
  "ambientocclusion": false,
  "textures": {
    "particle": "scp_restoration:block/light_gray",
    "texture": "scp_restoration:block/light_gray"
  },
  "elements": [
    {
      "from": [
        7,
        7,
        7
      ],
      "to": [
        9,
        9,
        9
      ],
      "faces": {
        "north": {
          "uv": [
            2,
            2,
            14,
            14
          ],
          "texture": "#texture"
        },
        "east": {
          "uv": [
            2,
            2,
            14,
            14
          ],
          "texture": "#texture"
        },
        "south": {
          "uv": [
            2,
            2,
            14,
            14
          ],
          "texture": "#texture"
        },
        "west": {
          "uv": [
            2,
            2,
            14,
            14
          ],
          "texture": "#texture"
        },
        "up": {
          "uv": [
            2,
            2,
            14,
            14
          ],
          "texture": "#texture"
        },
        "down": {
          "uv": [
            14,
            14,
            2,
            2
          ],
          "texture": "#texture"
        }
      }
    }
  ]
}